tangled_adjudicate/__init__.py
tangled_adjudicate/adjudicators/__init__.py
tangled_adjudicate/adjudicators/adjudicate.py
tangled_adjudicate/schrodinger/__init__.py
tangled_adjudicate/schrodinger/new_schedule.txt
tangled_adjudicate/schrodinger/schrodinger_functions.py
tangled_adjudicate/schrodinger/sparse_matrices.py
tangled_adjudicate/utils/__init__.py
tangled_adjudicate/utils/adjudicate_all_terminal_states.py
tangled_adjudicate/utils/compare_adjudication_results.py
tangled_adjudicate/utils/find_graph_automorphisms.py
tangled_adjudicate/utils/find_hardware_embeddings.py
tangled_adjudicate/utils/game_graph_properties.py
tangled_adjudicate/utils/generate_terminal_states.py
tangled_adjudicate/utils/how_to_adjudicate_states.py
tangled_adjudicate/utils/parameters.py
tangled_adjudicate/utils/utilities.py
tests/__init__.py
tangled_adjudicate-0.0.1.dist-info/LICENSE
tangled_adjudicate-0.0.1.dist-info/METADATA
tangled_adjudicate-0.0.1.dist-info/WHEEL
tangled_adjudicate-0.0.1.dist-info/RECORD
