Metadata-Version: 2.1
Name: tangled-adjudicate
Version: 0.0.1
Summary: Tangled adjudicators
Home-page: https://www.snowdropquantum.com/
License: MIT
Author: Geordie Rose
Author-email: geordie@snowdropquantum.com
Requires-Python: >=3.8,<4.0
Classifier: License :: OSI Approved :: MIT License
Classifier: Programming Language :: Python :: 3
Classifier: Programming Language :: Python :: 3.8
Classifier: Programming Language :: Python :: 3.9
Classifier: Programming Language :: Python :: 3.10
Classifier: Programming Language :: Python :: 3.11
Classifier: Programming Language :: Python :: 3.12
Classifier: Programming Language :: Python :: 3.13
Requires-Dist: dwave-ocean-sdk
Requires-Dist: gdown
Requires-Dist: matplotlib
